pipeline_data/__init__.py
pipeline_data/lock.py
pipeline_data/pipeline.py
pipeline_data/sqla_decorator/__init__.py
pipeline_data/sqla_decorator/engine.py
pipeline_data/sqla_decorator/manager.py
pipeline_data/sqla_decorator/models.py
pipeline_data/sqla_decorator/session_ctx.py
pipeline_data/sqla_decorator/utils/__init__.py
pipeline_data/sqla_decorator/utils/db.py
pipeline_data/sqla_decorator/utils/explain.py
pipeline_data/sqla_decorator/utils/query_count.py
pipeline_data/sqla_decorator/utils/tool.py
pipeline_data-1.2.4.dist-info/METADATA
pipeline_data-1.2.4.dist-info/WHEEL
pipeline_data-1.2.4.dist-info/top_level.txt
pipeline_data-1.2.4.dist-info/RECORD
