Metadata-Version: 2.1
Name: pipeline-data
Version: 1.2.4
Summary: 数据同步
Author: zhongbiao
Requires-Dist: sqlalchemy (~=1.4.0)
Requires-Dist: pottery (==3.0.0)
Requires-Dist: werkzeug
Requires-Dist: regex (==2022.7.25)
Requires-Dist: cchardet (==2.1.7)
Requires-Dist: pymysql (==0.9.3)
